{
    "top_artists": [
        {
            "artist_id": "2YZyLoL8N0Wb9xBt1NhZWg",
            "artist_name": "Kendrick Lamar",
            "image_url": "https://i.scdn.co/image/ab6761610000e5eb437b9e2a82505b3d93ff1022",
            "top_tracks": [
                {
                    "track_name": "Not Like Us",
                    "track_id": "6AI3ezQ4o3HUoP6Dhudph3",
                    "album_id": "5JjnoGJyOxfSZUZtk2rRwZ"
                },
                {
                    "track_name": "Like That",
                    "track_id": "2tudvzsrR56uom6smgOcSf",
                    "album_id": "4iqbFIdGOTzXeDtt9owjQn"
                },
                {
                    "track_name": "euphoria",
                    "track_id": "77DRzu7ERs0TX3roZcre7Q",
                    "album_id": "32bR4LcEc1PvJEhaKoo4ZN"
                },
                {
                    "track_name": "All The Stars (with SZA)",
                    "track_id": "3GCdLUSnKSMJhs4Tj6CV3s",
                    "album_id": "3pLdWdkj83EYfDN6H2N8MR"
                },
                {
                    "track_name": "Money Trees",
                    "track_id": "74tLlkN3rgVzRqQJgPfink",
                    "album_id": "0Oq3mWfexhsjUh0aNNBB5u"
                },
                {
                    "track_name": "meet the grahams",
                    "track_id": "4S8PxReB1UiDR2F5x1lyIR",
                    "album_id": "5PGH88Cwual1Nj8d2RsKP0"
                },
                {
                    "track_name": "HUMBLE.",
                    "track_id": "7KXjTSCq5nL1LoYtL7XAwS",
                    "album_id": "4eLPsYPBmXABThSJ821sqY"
                },
                {
                    "track_name": "PRIDE.",
                    "track_id": "6IZvVAP7VPPnsGX6bvgkqg",
                    "album_id": "4eLPsYPBmXABThSJ821sqY"
                },
                {
                    "track_name": "LOVE. FEAT. ZACARI.",
                    "track_id": "6PGoSes0D9eUDeeAafB2As",
                    "album_id": "4eLPsYPBmXABThSJ821sqY"
                },
                {
                    "track_name": "family ties (with Kendrick Lamar)",
                    "track_id": "3QFInJAm9eyaho5vBzxInN",
                    "album_id": "3r46DPIQeBQbjvjjV5mXGg"
                }
            ]
        },
        {
            "artist_id": "6vWDO969PvNqNYHIOW5v0m",
            "artist_name": "Beyoncé",
            "image_url": "https://i.scdn.co/image/ab6761610000e5eb247f44069c0bd1781df2f785",
            "top_tracks": [
                {
                    "track_name": "TEXAS HOLD 'EM",
                    "track_id": "7wLShogStyDeZvL0a6daN5",
                    "album_id": "6BzxX6zkDsYKFJ04ziU5xQ"
                },
                {
                    "track_name": "Crazy In Love (feat. Jay-Z)",
                    "track_id": "0TwBtDAWpkpM3srywFVOV5",
                    "album_id": "06v9eHnqhMK2tbM2Iz3p0Y"
                },
                {
                    "track_name": "II MOST WANTED",
                    "track_id": "6zuPQl2RVqQ4y5nAH61CFC",
                    "album_id": "2m1enA3YrMLVvR3q0MqLpL"
                },
                {
                    "track_name": "Halo",
                    "track_id": "2CvOqDpQIMw69cCzWqr5yr",
                    "album_id": "3ROfBX6lJLnCmaw1NrP5K9"
                },
                {
                    "track_name": "BODYGUARD",
                    "track_id": "6Y4rniIxibegzsg8cdWAWV",
                    "album_id": "6BzxX6zkDsYKFJ04ziU5xQ"
                },
                {
                    "track_name": "JOLENE",
                    "track_id": "1VxEaXbIq3xAvqh80xP67w",
                    "album_id": "2m1enA3YrMLVvR3q0MqLpL"
                },
                {
                    "track_name": "CUFF IT",
                    "track_id": "1xzi1Jcr7mEi9K2RfzLOqS",
                    "album_id": "6FJxoadUE4JNVwWHghBwnb"
                },
                {
                    "track_name": "LEVII'S JEANS",
                    "track_id": "2UDARQiksl207HcSduDpov",
                    "album_id": "6BzxX6zkDsYKFJ04ziU5xQ"
                },
                {
                    "track_name": "YA YA",
                    "track_id": "0K9tfzrxJyCQIf7oAlPwaK",
                    "album_id": "6BzxX6zkDsYKFJ04ziU5xQ"
                },
                {
                    "track_name": "16 CARRIAGES",
                    "track_id": "7x5ziCOQFir0AQN8dFisK6",
                    "album_id": "2m1enA3YrMLVvR3q0MqLpL"
                }
            ]
        },
        {
            "artist_id": "1Xyo4u8uXC1ZmMpatF05PJ",
            "artist_name": "The Weeknd",
            "image_url": "https://i.scdn.co/image/ab6761610000e5eb214f3cf1cbe7139c1e26ffbb",
            "top_tracks": [
                {
                    "track_name": "One Of The Girls (with JENNIE, Lily Rose Depp)",
                    "track_id": "7CyPwkp0oE8Ro9Dd5CUDjW",
                    "album_id": "7tzVd1fwkxsorytCBjEJkU"
                },
                {
                    "track_name": "Starboy",
                    "track_id": "7MXVkk9YMctZqd1Srtv4MB",
                    "album_id": "2ODvWsOgouMbaA5xf0RkJe"
                },
                {
                    "track_name": "Blinding Lights",
                    "track_id": "0VjIjW4GlUZAMYd2vXMi3b",
                    "album_id": "4yP0hdKOZPNshxUOjY0cZj"
                },
                {
                    "track_name": "Die For You",
                    "track_id": "2LBqCSwhJGcFQeTHMVGwy3",
                    "album_id": "4AdZV63ycxFLF6Hcol0QnB"
                },
                {
                    "track_name": "Popular (with Playboi Carti & Madonna) - From The Idol Vol. 1 (Music from the HBO Original Series)",
                    "track_id": "6WzRpISELf3YglGAh7TXcG",
                    "album_id": "5O0zUvdnJr0RbWzLFneN2i"
                },
                {
                    "track_name": "Stargirl Interlude",
                    "track_id": "5gDWsRxpJ2lZAffh5p7K0w",
                    "album_id": "4AdZV63ycxFLF6Hcol0QnB"
                },
                {
                    "track_name": "Save Your Tears",
                    "track_id": "5QO79kh1waicV47BqGRL3g",
                    "album_id": "4yP0hdKOZPNshxUOjY0cZj"
                },
                {
                    "track_name": "Creepin' (with The Weeknd & 21 Savage)",
                    "track_id": "2dHHgzDwk4BJdRwy9uXhTO",
                    "album_id": "7txGsnDSqVMoRl6RQ9XyZP"
                },
                {
                    "track_name": "The Hills",
                    "track_id": "7fBv7CLKzipRk6EC6TWHOB",
                    "album_id": "0P3oVJBFOv3TDXlYRhGL7s"
                },
                {
                    "track_name": "Call Out My Name",
                    "track_id": "09mEdoA6zrmBPgTEN5qXmN",
                    "album_id": "4qZBW3f2Q8y0k1A84d4iAO"
                }
            ]
        },
        {
            "artist_id": "06HL4z0CvFAxyc27GXpf02",
            "artist_name": "Taylor Swift",
            "image_url": "https://i.scdn.co/image/ab6761610000e5ebe672b5f553298dcdccb0e676",
            "top_tracks": [
                {
                    "track_name": "Fortnight (feat. Post Malone)",
                    "track_id": "2OzhQlSqBEmt7hmkYxfT6m",
                    "album_id": "1Mo4aZ8pdj6L1jx8zSwJnt"
                },
                {
                    "track_name": "I Can Do It With a Broken Heart",
                    "track_id": "4q5YezDOIPcoLr8R81x9qy",
                    "album_id": "1Mo4aZ8pdj6L1jx8zSwJnt"
                },
                {
                    "track_name": "Cruel Summer",
                    "track_id": "1BxfuPKGuaTgP7aM0Bbdwr",
                    "album_id": "1NAmidJlEaVgA3MpcPFYGq"
                },
                {
                    "track_name": "Down Bad",
                    "track_id": "2F3N9tdombb64aW6VtZOdo",
                    "album_id": "1Mo4aZ8pdj6L1jx8zSwJnt"
                },
                {
                    "track_name": "So Long, London",
                    "track_id": "3Vevii7qKqrmW8CcyzBHDl",
                    "album_id": "1Mo4aZ8pdj6L1jx8zSwJnt"
                },
                {
                    "track_name": "Who’s Afraid of Little Old Me?",
                    "track_id": "36t6frENUtCYKuZus6aYDO",
                    "album_id": "1Mo4aZ8pdj6L1jx8zSwJnt"
                },
                {
                    "track_name": "Guilty as Sin?",
                    "track_id": "0W0iAC1VGlB82PI6elxFYf",
                    "album_id": "1Mo4aZ8pdj6L1jx8zSwJnt"
                },
                {
                    "track_name": "My Boy Only Breaks His Favorite Toys",
                    "track_id": "2XXwLdtuAcE0HSCu61ijAb",
                    "album_id": "1Mo4aZ8pdj6L1jx8zSwJnt"
                },
                {
                    "track_name": "But Daddy I Love Him",
                    "track_id": "5og4Qzt92jJzVDkOtSEilb",
                    "album_id": "1Mo4aZ8pdj6L1jx8zSwJnt"
                },
                {
                    "track_name": "The Tortured Poets Department",
                    "track_id": "3NMrVbIVWT3fPXBj0rNDKG",
                    "album_id": "1Mo4aZ8pdj6L1jx8zSwJnt"
                }
            ]
        },
        {
            "artist_id": "5K4W6rqBFWDnAN6FQUkS6x",
            "artist_name": "Kanye West",
            "image_url": "https://i.scdn.co/image/ab6761610000e5eb6e835a500e791bf9c27a422a",
            "top_tracks": [
                {
                    "track_name": "CARNIVAL",
                    "track_id": "3w0w2T288dec0mgeZZqoNN",
                    "album_id": "30zwjSQEodaUXCn11nmiVF"
                },
                {
                    "track_name": "Heartless",
                    "track_id": "4EWCNWgDS8707fNSZ1oaA5",
                    "album_id": "3WFTGIO6E3Xh4paEOBY9OU"
                },
                {
                    "track_name": "Flashing Lights",
                    "track_id": "5TRPicyLGbAF2LGBFbHGvO",
                    "album_id": "4SZko61aMnmgvNhfhgTuD3"
                },
                {
                    "track_name": "Father Stretch My Hands Pt. 1",
                    "track_id": "4KW1lqgSr8TKrvBII0Brf8",
                    "album_id": "7gsWAHLeT0w7es6FofOXk1"
                },
                {
                    "track_name": "Runaway",
                    "track_id": "3DK6m7It6Pw857FcQftMds",
                    "album_id": "20r762YmB5HeofjMCiPMLv"
                },
                {
                    "track_name": "I Wonder",
                    "track_id": "7rbECVPkY5UODxoOUVKZnA",
                    "album_id": "4SZko61aMnmgvNhfhgTuD3"
                },
                {
                    "track_name": "Ni**as In Paris",
                    "track_id": "1auxYwYrFRqZP7t3s7w4um",
                    "album_id": "0OcMap99vLEeGkBCfCwRwS"
                },
                {
                    "track_name": "Bound 2",
                    "track_id": "3sNVsP50132BTNlImLx70i",
                    "album_id": "7D2NdGvBHIavgLhmcwhluK"
                },
                {
                    "track_name": "Homecoming",
                    "track_id": "4iz9lGMjU1lXS51oPmUmTe",
                    "album_id": "4SZko61aMnmgvNhfhgTuD3"
                },
                {
                    "track_name": "Gold Digger",
                    "track_id": "1PS1QMdUqOal0ai3Gt7sDQ",
                    "album_id": "5ll74bqtkcXlKE7wwkMq4g"
                }
            ]
        },
        {
            "artist_id": "3TVXtAsR1Inumwj472S9r4",
            "artist_name": "Drake",
            "image_url": "https://i.scdn.co/image/ab6761610000e5eb4293385d324db8558179afd9",
            "top_tracks": [
                {
                    "track_name": "Push Ups",
                    "track_id": "3eh51r6rFWAlGQRlHx9QnQ",
                    "album_id": "06me0leRR3AuF4IFiEytml"
                },
                {
                    "track_name": "One Dance",
                    "track_id": "1zi7xx7UVEFkmKfv06H8x0",
                    "album_id": "40GMAhriYJRO1rsY4YdrZb"
                },
                {
                    "track_name": "Family Matters",
                    "track_id": "1wFFFzJ5EsKbBWZriAcubN",
                    "album_id": "3qwCuSISrIUpyt6sB5edmQ"
                },
                {
                    "track_name": "Rich Baby Daddy (feat. Sexyy Red & SZA)",
                    "track_id": "1yeB8MUNeLo9Ek1UEpsyz6",
                    "album_id": "4czdORdCWP9umpbhFXK2fW"
                },
                {
                    "track_name": "Jimmy Cooks (feat. 21 Savage)",
                    "track_id": "3F5CgOj3wFlRv51JsHbxhe",
                    "album_id": "3cf4iSSKd8ffTncbtKljXw"
                },
                {
                    "track_name": "IDGAF (feat. Yeat)",
                    "track_id": "2YSzYUF3jWqb9YP9VXmpjE",
                    "album_id": "4czdORdCWP9umpbhFXK2fW"
                },
                {
                    "track_name": "Passionfruit",
                    "track_id": "5mCPDVBb16L4XQwDdbRUpz",
                    "album_id": "1lXY618HWkwYKJWBRYR4MK"
                },
                {
                    "track_name": "First Person Shooter (feat. J. Cole)",
                    "track_id": "7aqfrAY2p9BUSiupwk3svU",
                    "album_id": "4czdORdCWP9umpbhFXK2fW"
                },
                {
                    "track_name": "God's Plan",
                    "track_id": "6DCZcSspjsKoFjzjrWoCdn",
                    "album_id": "1ATL5GLyefJaxhQzSPVrLX"
                },
                {
                    "track_name": "WAIT FOR U (feat. Drake & Tems)",
                    "track_id": "59nOXPmaKlBfGMDeOVGrIK",
                    "album_id": "6tE9Dnp2zInFij4jKssysL"
                }
            ]
        },
        {
            "artist_id": "4V8LLVI7PbaPR0K2TGSxFF",
            "artist_name": "Tyler, The Creator",
            "image_url": "https://i.scdn.co/image/ab6761610000e5eb8278b782cbb5a3963db88ada",
            "top_tracks": [
                {
                    "track_name": "See You Again (feat. Kali Uchis)",
                    "track_id": "7KA4W4McWYRpgf0fWsJZWB",
                    "album_id": "2nkto6YNI4rUYTLqEwWJ3o"
                },
                {
                    "track_name": "BEST INTEREST",
                    "track_id": "3jHdKaLCkuNEkWcLVmQPCX",
                    "album_id": "5iUwaD3wFVwfaAfs9Z0eCh"
                },
                {
                    "track_name": "EARFQUAKE",
                    "track_id": "5hVghJ4KaYES3BFUATCYn0",
                    "album_id": "5zi7WsKlIiUXv09tbGLKsE"
                },
                {
                    "track_name": "She",
                    "track_id": "5WzfCu5fhgm7jv896EN1Md",
                    "album_id": "3CxknRPQLbOJRwQrNekNyU"
                },
                {
                    "track_name": "ARE WE STILL FRIENDS?",
                    "track_id": "5TxRUOsGeWeRl3xOML59Ai",
                    "album_id": "5zi7WsKlIiUXv09tbGLKsE"
                },
                {
                    "track_name": "NEW MAGIC WAND",
                    "track_id": "0fv2KH6hac06J86hBUTcSf",
                    "album_id": "5zi7WsKlIiUXv09tbGLKsE"
                },
                {
                    "track_name": "SWEET / I THOUGHT YOU WANTED TO DANCE (feat. Brent Faiyaz & Fana Hues)",
                    "track_id": "3EG9FJ0ToLfgnc1IG2Z1wz",
                    "album_id": "45ba6QAtNrdv6Ke4MFOKk9"
                },
                {
                    "track_name": "GONE, GONE / THANK YOU",
                    "track_id": "1hz7SRTGUNAtIQ46qiNv2p",
                    "album_id": "5zi7WsKlIiUXv09tbGLKsE"
                },
                {
                    "track_name": "WUSYANAME (feat. Youngboy Never Broke Again & Ty Dolla $ign)",
                    "track_id": "5B0kgjHULYJhAQkK5XsMoC",
                    "album_id": "45ba6QAtNrdv6Ke4MFOKk9"
                },
                {
                    "track_name": "RUNNING OUT OF TIME",
                    "track_id": "5QvBXUm5MglLJ3iBfTX2Wo",
                    "album_id": "5zi7WsKlIiUXv09tbGLKsE"
                }
            ]
        },
        {
            "artist_id": "00FQb4jTyendYWaN8pK0wa",
            "artist_name": "Lana Del Rey",
            "image_url": "https://i.scdn.co/image/ab6761610000e5ebb99cacf8acd5378206767261",
            "top_tracks": [
                {
                    "track_name": "Summertime Sadness",
                    "track_id": "3BJe4B8zGnqEdQPMvfVjuS",
                    "album_id": "5VoeRuTrGhTbKelUfwymwu"
                },
                {
                    "track_name": "Young And Beautiful",
                    "track_id": "2nMeu6UenVvwUktBCpLMK9",
                    "album_id": "1D92WOHWUI2AGQCCdplcXL"
                },
                {
                    "track_name": "Say Yes To Heaven",
                    "track_id": "6GGtHZgBycCgGBUhZo81xe",
                    "album_id": "6jVg0POvGYH1Pt6lISl3ok"
                },
                {
                    "track_name": "West Coast",
                    "track_id": "5Y6nVaayzitvsD5F7nr3DV",
                    "album_id": "1ORxRsK3MrSLvh7VQTF01F"
                },
                {
                    "track_name": "Video Games",
                    "track_id": "0fBSs3fRoh1yJcne77fdu9",
                    "album_id": "5VoeRuTrGhTbKelUfwymwu"
                },
                {
                    "track_name": "Cinnamon Girl",
                    "track_id": "2mdEsXPu8ZmkHRRtAdC09e",
                    "album_id": "5XpEKORZ4y6OrCZSKsi46A"
                },
                {
                    "track_name": "Radio",
                    "track_id": "3taCbWWTilb7eNMsAzOBq4",
                    "album_id": "5VoeRuTrGhTbKelUfwymwu"
                },
                {
                    "track_name": "Diet Mountain Dew",
                    "track_id": "2vtmY2mSccRzKGjtcHSzI3",
                    "album_id": "5VoeRuTrGhTbKelUfwymwu"
                },
                {
                    "track_name": "Brooklyn Baby",
                    "track_id": "1NZs6n6hl8UuMaX0UC0YTz",
                    "album_id": "1ORxRsK3MrSLvh7VQTF01F"
                },
                {
                    "track_name": "Let The Light In (feat. Father John Misty)",
                    "track_id": "4qG7hWhljsqqENL5PaLA2z",
                    "album_id": "5HOHne1wzItQlIYmLXLYfZ"
                }
            ]
        },
        {
            "artist_id": "6qqNVTkY8uBg9cP3Jd7DAH",
            "artist_name": "Billie Eilish",
            "image_url": "https://i.scdn.co/image/ab6761610000e5eb4a21b4760d2ecb7b0dcdc8da",
            "top_tracks": [
                {
                    "track_name": "LUNCH",
                    "track_id": "629DixmZGHc7ILtEntuiWE",
                    "album_id": "7aJuG4TFXa2hmE4z1yxc3n"
                },
                {
                    "track_name": "CHIHIRO",
                    "track_id": "7BRD7x5pt8Lqa1eGYC4dzj",
                    "album_id": "7aJuG4TFXa2hmE4z1yxc3n"
                },
                {
                    "track_name": "BIRDS OF A FEATHER",
                    "track_id": "6dOtVTDdiauQNBQEDOtlAB",
                    "album_id": "7aJuG4TFXa2hmE4z1yxc3n"
                },
                {
                    "track_name": "WILDFLOWER",
                    "track_id": "3QaPy1KgI7nu9FJEQUgn6h",
                    "album_id": "7aJuG4TFXa2hmE4z1yxc3n"
                },
                {
                    "track_name": "BLUE",
                    "track_id": "2prqm9sPLj10B4Wg0wE5x9",
                    "album_id": "7aJuG4TFXa2hmE4z1yxc3n"
                },
                {
                    "track_name": "SKINNY",
                    "track_id": "1CsMKhwEmNnmvHUuO5nryA",
                    "album_id": "7aJuG4TFXa2hmE4z1yxc3n"
                },
                {
                    "track_name": "L’AMOUR DE MA VIE",
                    "track_id": "6fPan2saHdFaIHuTSatORv",
                    "album_id": "7aJuG4TFXa2hmE4z1yxc3n"
                },
                {
                    "track_name": "THE GREATEST",
                    "track_id": "6TGd66r0nlPaYm3KIoI7ET",
                    "album_id": "7aJuG4TFXa2hmE4z1yxc3n"
                },
                {
                    "track_name": "What Was I Made For? [From The Motion Picture \"Barbie\"]",
                    "track_id": "6wf7Yu7cxBSPrRlWeSeK0Q",
                    "album_id": "3AafSrFIbJPH6BJHiJm1Cd"
                },
                {
                    "track_name": "THE DINER",
                    "track_id": "1LLUoftvmTjVNBHZoQyveF",
                    "album_id": "7aJuG4TFXa2hmE4z1yxc3n"
                }
            ]
        },
        {
            "artist_id": "6qqNVTkY8uBg9cP3Jd7DAH",
            "artist_name": "Billie Eilish",
            "image_url": "https://i.scdn.co/image/ab6761610000e5eb4a21b4760d2ecb7b0dcdc8da",
            "top_tracks": [
                {
                    "track_name": "LUNCH",
                    "track_id": "629DixmZGHc7ILtEntuiWE",
                    "album_id": "7aJuG4TFXa2hmE4z1yxc3n"
                },
                {
                    "track_name": "CHIHIRO",
                    "track_id": "7BRD7x5pt8Lqa1eGYC4dzj",
                    "album_id": "7aJuG4TFXa2hmE4z1yxc3n"
                },
                {
                    "track_name": "BIRDS OF A FEATHER",
                    "track_id": "6dOtVTDdiauQNBQEDOtlAB",
                    "album_id": "7aJuG4TFXa2hmE4z1yxc3n"
                },
                {
                    "track_name": "WILDFLOWER",
                    "track_id": "3QaPy1KgI7nu9FJEQUgn6h",
                    "album_id": "7aJuG4TFXa2hmE4z1yxc3n"
                },
                {
                    "track_name": "BLUE",
                    "track_id": "2prqm9sPLj10B4Wg0wE5x9",
                    "album_id": "7aJuG4TFXa2hmE4z1yxc3n"
                },
                {
                    "track_name": "SKINNY",
                    "track_id": "1CsMKhwEmNnmvHUuO5nryA",
                    "album_id": "7aJuG4TFXa2hmE4z1yxc3n"
                },
                {
                    "track_name": "L’AMOUR DE MA VIE",
                    "track_id": "6fPan2saHdFaIHuTSatORv",
                    "album_id": "7aJuG4TFXa2hmE4z1yxc3n"
                },
                {
                    "track_name": "THE GREATEST",
                    "track_id": "6TGd66r0nlPaYm3KIoI7ET",
                    "album_id": "7aJuG4TFXa2hmE4z1yxc3n"
                },
                {
                    "track_name": "What Was I Made For? [From The Motion Picture \"Barbie\"]",
                    "track_id": "6wf7Yu7cxBSPrRlWeSeK0Q",
                    "album_id": "3AafSrFIbJPH6BJHiJm1Cd"
                },
                {
                    "track_name": "THE DINER",
                    "track_id": "1LLUoftvmTjVNBHZoQyveF",
                    "album_id": "7aJuG4TFXa2hmE4z1yxc3n"
                }
            ]
        },
        {
            "artist_id": "5pKCCKE2ajJHZ9KAiaK11H",
            "artist_name": "Rihanna",
            "image_url": "https://i.scdn.co/image/ab6761610000e5eb99e4fca7c0b7cb166d915789",
            "top_tracks": [
                {
                    "track_name": "We Found Love",
                    "track_id": "6qn9YLKt13AGvpq9jfO8py",
                    "album_id": "2g1EakEaW7fPTZC6vBmBCn"
                },
                {
                    "track_name": "This Is What You Came For",
                    "track_id": "0azC730Exh71aQlOt9Zj3y",
                    "album_id": "3pEgGUv379EDinvg1TN7Kt"
                },
                {
                    "track_name": "Only Girl (In The World)",
                    "track_id": "2ENexcMEMsYk0rVJigVD3i",
                    "album_id": "5QG3tjE5L9F6O2vCAPph38"
                },
                {
                    "track_name": "Umbrella",
                    "track_id": "49FYlytm3dAAraYgpoJZux",
                    "album_id": "3JSWZWeTHF4HDGt5Eozdy7"
                },
                {
                    "track_name": "S&M",
                    "track_id": "7ySUcLPVX7KudhnmNcgY2D",
                    "album_id": "5QG3tjE5L9F6O2vCAPph38"
                },
                {
                    "track_name": "Love On The Brain",
                    "track_id": "5oO3drDxtziYU2H1X23ZIp",
                    "album_id": "4UlGauD7ROb3YbVOFMgW5u"
                },
                {
                    "track_name": "Don't Stop The Music",
                    "track_id": "0ByMNEPAPpOR5H69DVrTNy",
                    "album_id": "3JSWZWeTHF4HDGt5Eozdy7"
                },
                {
                    "track_name": "Diamonds",
                    "track_id": "7i0jaBLpIADxqNbhAb4XFb",
                    "album_id": "5UDXzVwWnn3mDy3mTpQPYb"
                },
                {
                    "track_name": "Stay",
                    "track_id": "2Yy0FsAV2I5VXU4xpph2WN",
                    "album_id": "5UDXzVwWnn3mDy3mTpQPYb"
                },
                {
                    "track_name": "Needed Me",
                    "track_id": "4pAl7FkDMNBsjykPXo91B3",
                    "album_id": "4UlGauD7ROb3YbVOFMgW5u"
                }
            ]
        },
        {
            "artist_id": "6qqNVTkY8uBg9cP3Jd7DAH",
            "artist_name": "Billie Eilish",
            "image_url": "https://i.scdn.co/image/ab6761610000e5eb4a21b4760d2ecb7b0dcdc8da",
            "top_tracks": [
                {
                    "track_name": "LUNCH",
                    "track_id": "629DixmZGHc7ILtEntuiWE",
                    "album_id": "7aJuG4TFXa2hmE4z1yxc3n"
                },
                {
                    "track_name": "CHIHIRO",
                    "track_id": "7BRD7x5pt8Lqa1eGYC4dzj",
                    "album_id": "7aJuG4TFXa2hmE4z1yxc3n"
                },
                {
                    "track_name": "BIRDS OF A FEATHER",
                    "track_id": "6dOtVTDdiauQNBQEDOtlAB",
                    "album_id": "7aJuG4TFXa2hmE4z1yxc3n"
                },
                {
                    "track_name": "WILDFLOWER",
                    "track_id": "3QaPy1KgI7nu9FJEQUgn6h",
                    "album_id": "7aJuG4TFXa2hmE4z1yxc3n"
                },
                {
                    "track_name": "BLUE",
                    "track_id": "2prqm9sPLj10B4Wg0wE5x9",
                    "album_id": "7aJuG4TFXa2hmE4z1yxc3n"
                },
                {
                    "track_name": "SKINNY",
                    "track_id": "1CsMKhwEmNnmvHUuO5nryA",
                    "album_id": "7aJuG4TFXa2hmE4z1yxc3n"
                },
                {
                    "track_name": "L’AMOUR DE MA VIE",
                    "track_id": "6fPan2saHdFaIHuTSatORv",
                    "album_id": "7aJuG4TFXa2hmE4z1yxc3n"
                },
                {
                    "track_name": "THE GREATEST",
                    "track_id": "6TGd66r0nlPaYm3KIoI7ET",
                    "album_id": "7aJuG4TFXa2hmE4z1yxc3n"
                },
                {
                    "track_name": "What Was I Made For? [From The Motion Picture \"Barbie\"]",
                    "track_id": "6wf7Yu7cxBSPrRlWeSeK0Q",
                    "album_id": "3AafSrFIbJPH6BJHiJm1Cd"
                },
                {
                    "track_name": "THE DINER",
                    "track_id": "1LLUoftvmTjVNBHZoQyveF",
                    "album_id": "7aJuG4TFXa2hmE4z1yxc3n"
                }
            ]
        },
        {
            "artist_id": "1Xyo4u8uXC1ZmMpatF05PJ",
            "artist_name": "The Weeknd",
            "image_url": "https://i.scdn.co/image/ab6761610000e5eb214f3cf1cbe7139c1e26ffbb",
            "top_tracks": [
                {
                    "track_name": "One Of The Girls (with JENNIE, Lily Rose Depp)",
                    "track_id": "7CyPwkp0oE8Ro9Dd5CUDjW",
                    "album_id": "7tzVd1fwkxsorytCBjEJkU"
                },
                {
                    "track_name": "Starboy",
                    "track_id": "7MXVkk9YMctZqd1Srtv4MB",
                    "album_id": "2ODvWsOgouMbaA5xf0RkJe"
                },
                {
                    "track_name": "Blinding Lights",
                    "track_id": "0VjIjW4GlUZAMYd2vXMi3b",
                    "album_id": "4yP0hdKOZPNshxUOjY0cZj"
                },
                {
                    "track_name": "Die For You",
                    "track_id": "2LBqCSwhJGcFQeTHMVGwy3",
                    "album_id": "4AdZV63ycxFLF6Hcol0QnB"
                },
                {
                    "track_name": "Popular (with Playboi Carti & Madonna) - From The Idol Vol. 1 (Music from the HBO Original Series)",
                    "track_id": "6WzRpISELf3YglGAh7TXcG",
                    "album_id": "5O0zUvdnJr0RbWzLFneN2i"
                },
                {
                    "track_name": "Stargirl Interlude",
                    "track_id": "5gDWsRxpJ2lZAffh5p7K0w",
                    "album_id": "4AdZV63ycxFLF6Hcol0QnB"
                },
                {
                    "track_name": "Save Your Tears",
                    "track_id": "5QO79kh1waicV47BqGRL3g",
                    "album_id": "4yP0hdKOZPNshxUOjY0cZj"
                },
                {
                    "track_name": "Creepin' (with The Weeknd & 21 Savage)",
                    "track_id": "2dHHgzDwk4BJdRwy9uXhTO",
                    "album_id": "7txGsnDSqVMoRl6RQ9XyZP"
                },
                {
                    "track_name": "The Hills",
                    "track_id": "7fBv7CLKzipRk6EC6TWHOB",
                    "album_id": "0P3oVJBFOv3TDXlYRhGL7s"
                },
                {
                    "track_name": "Call Out My Name",
                    "track_id": "09mEdoA6zrmBPgTEN5qXmN",
                    "album_id": "4qZBW3f2Q8y0k1A84d4iAO"
                }
            ]
        },
        {
            "artist_id": "7Ln80lUS6He07XvHI8qqHH",
            "artist_name": "Arctic Monkeys",
            "image_url": "https://i.scdn.co/image/ab6761610000e5eb7da39dea0a72f581535fb11f",
            "top_tracks": [
                {
                    "track_name": "I Wanna Be Yours",
                    "track_id": "5XeFesFbtLpXzIVDNQP22n",
                    "album_id": "78bpIziExqiI9qztvNFlQu"
                },
                {
                    "track_name": "505",
                    "track_id": "0BxE4FqsDD1Ot4YuBXwAPp",
                    "album_id": "1XkGORuUX2QGOEIL4EbJKm"
                },
                {
                    "track_name": "Do I Wanna Know?",
                    "track_id": "5FVd6KXrgO9B3JPmC8OPst",
                    "album_id": "78bpIziExqiI9qztvNFlQu"
                },
                {
                    "track_name": "Why'd You Only Call Me When You're High?",
                    "track_id": "086myS9r57YsLbJpU0TgK9",
                    "album_id": "78bpIziExqiI9qztvNFlQu"
                },
                {
                    "track_name": "R U Mine?",
                    "track_id": "2AT8iROs4FQueDv2c8q2KE",
                    "album_id": "78bpIziExqiI9qztvNFlQu"
                },
                {
                    "track_name": "Fluorescent Adolescent",
                    "track_id": "2x8evxqUlF0eRabbW2JBJd",
                    "album_id": "1XkGORuUX2QGOEIL4EbJKm"
                },
                {
                    "track_name": "Snap Out Of It",
                    "track_id": "0NdTUS4UiNYCNn5FgVqKQY",
                    "album_id": "78bpIziExqiI9qztvNFlQu"
                },
                {
                    "track_name": "Arabella",
                    "track_id": "7nzsY8vlnKdvGOEE0rjAXZ",
                    "album_id": "78bpIziExqiI9qztvNFlQu"
                },
                {
                    "track_name": "Knee Socks",
                    "track_id": "2LGdO5MtFdyphi2EihANZG",
                    "album_id": "78bpIziExqiI9qztvNFlQu"
                },
                {
                    "track_name": "Mardy Bum",
                    "track_id": "2fyIS6GXMgUcSv4oejx63f",
                    "album_id": "50Zz8CkIhATKUlQMbHO3k1"
                }
            ]
        },
        {
            "artist_id": "4Z8W4fKeB5YxbusRsdQVPb",
            "artist_name": "Radiohead",
            "image_url": "https://i.scdn.co/image/ab6761610000e5eba03696716c9ee605006047fd",
            "top_tracks": [
                {
                    "track_name": "Creep",
                    "track_id": "70LcF31zb1H0PyJoS1Sx1r",
                    "album_id": "3gBVdu4a1MMJVMy6vwPEb8"
                },
                {
                    "track_name": "No Surprises",
                    "track_id": "10nyNJ6zNy2YVYLrcwLccB",
                    "album_id": "6dVIqQ8qmQ5GBnJ9shOYGE"
                },
                {
                    "track_name": "Karma Police",
                    "track_id": "63OQupATfueTdZMWTxW03A",
                    "album_id": "6dVIqQ8qmQ5GBnJ9shOYGE"
                },
                {
                    "track_name": "High and Dry",
                    "track_id": "2a1iMaoWQ5MnvLFBDv4qkf",
                    "album_id": "35UJLpClj5EDrhpNIi4DFg"
                },
                {
                    "track_name": "Jigsaw Falling Into Place",
                    "track_id": "0YJ9FWWHn9EfnN0lHwbzvV",
                    "album_id": "5vkqYmiPBYLaalcmjujWxK"
                },
                {
                    "track_name": "Exit Music (For A Film)",
                    "track_id": "0z1o5L7HJx562xZSATcIpY",
                    "album_id": "6dVIqQ8qmQ5GBnJ9shOYGE"
                },
                {
                    "track_name": "Fake Plastic Trees",
                    "track_id": "73CKjW3vsUXRpy3NnX4H7F",
                    "album_id": "35UJLpClj5EDrhpNIi4DFg"
                },
                {
                    "track_name": "Weird Fishes/ Arpeggi",
                    "track_id": "4wajJ1o7jWIg62YqpkHC7S",
                    "album_id": "5vkqYmiPBYLaalcmjujWxK"
                },
                {
                    "track_name": "Just",
                    "track_id": "1dyTcli07c77mtQK3ahUZR",
                    "album_id": "35UJLpClj5EDrhpNIi4DFg"
                },
                {
                    "track_name": "All I Need",
                    "track_id": "5Qv2Nby1xTr9pQyjkrc94J",
                    "album_id": "5vkqYmiPBYLaalcmjujWxK"
                }
            ]
        },
        {
            "artist_id": "1RyvyyTE3xzB2ZywiAwp0i",
            "artist_name": "Future",
            "image_url": "https://i.scdn.co/image/ab6761610000e5eb6ef89e23678018c6d8630825",
            "top_tracks": [
                {
                    "track_name": "Like That",
                    "track_id": "2tudvzsrR56uom6smgOcSf",
                    "album_id": "4iqbFIdGOTzXeDtt9owjQn"
                },
                {
                    "track_name": "Type Shit",
                    "track_id": "28drn6tQo95MRvO0jQEo5C",
                    "album_id": "4iqbFIdGOTzXeDtt9owjQn"
                },
                {
                    "track_name": "Too Many Nights (feat. Don Toliver & with Future)",
                    "track_id": "2Hh3ETdQKrmSI3QS0hme7g",
                    "album_id": "7txGsnDSqVMoRl6RQ9XyZP"
                },
                {
                    "track_name": "Cinderella",
                    "track_id": "0hKtu53OlIFXVuYkZwcn3o",
                    "album_id": "4iqbFIdGOTzXeDtt9owjQn"
                },
                {
                    "track_name": "Superhero (Heroes & Villains) [with Future & Chris Brown]",
                    "track_id": "0vjeOZ3Ft5jvAi9SBFJm1j",
                    "album_id": "7txGsnDSqVMoRl6RQ9XyZP"
                },
                {
                    "track_name": "We Still Don't Trust You",
                    "track_id": "7sVbKoBdhXtYCEOO6qC1SN",
                    "album_id": "3bSNhnaQQXpC639OQ4pMyP"
                },
                {
                    "track_name": "WAIT FOR U (feat. Drake & Tems)",
                    "track_id": "59nOXPmaKlBfGMDeOVGrIK",
                    "album_id": "6tE9Dnp2zInFij4jKssysL"
                },
                {
                    "track_name": "Mask Off",
                    "track_id": "0VgkVdmE4gld66l8iyGjgx",
                    "album_id": "17FBoXK1NU2rvJBbzdzw0r"
                },
                {
                    "track_name": "TELEKINESIS (feat. SZA & Future)",
                    "track_id": "1i9lZvlaDdWDPyXEE95aiq",
                    "album_id": "18NOKLkZETa4sWwLMIm0UZ"
                },
                {
                    "track_name": "Young Metro",
                    "track_id": "3OxL6MuctgZp1e0zxoAZhH",
                    "album_id": "4iqbFIdGOTzXeDtt9owjQn"
                }
            ]
        },
        {
            "artist_id": "0Y5tJX1MQlPlqiwlOH1tJY",
            "artist_name": "Travis Scott",
            "image_url": "https://i.scdn.co/image/ab6761610000e5eb19c2790744c792d05570bb71",
            "top_tracks": [
                {
                    "track_name": "FE!N (feat. Playboi Carti)",
                    "track_id": "42VsgItocQwOQC3XWZ8JNA",
                    "album_id": "18NOKLkZETa4sWwLMIm0UZ"
                },
                {
                    "track_name": "Type Shit",
                    "track_id": "28drn6tQo95MRvO0jQEo5C",
                    "album_id": "4iqbFIdGOTzXeDtt9owjQn"
                },
                {
                    "track_name": "goosebumps",
                    "track_id": "6gBFPUFcJLzWGx4lenP6h2",
                    "album_id": "42WVQWuf1teDysXiOupIZt"
                },
                {
                    "track_name": "I KNOW ?",
                    "track_id": "6wsqVwoiVH2kde4k4KKAFU",
                    "album_id": "18NOKLkZETa4sWwLMIm0UZ"
                },
                {
                    "track_name": "Cinderella",
                    "track_id": "0hKtu53OlIFXVuYkZwcn3o",
                    "album_id": "4iqbFIdGOTzXeDtt9owjQn"
                },
                {
                    "track_name": "BUTTERFLY EFFECT",
                    "track_id": "2cYqizR4lgvp4Qu6IQ3qGN",
                    "album_id": "41GuZcammIkupMPKH2OJ6I"
                },
                {
                    "track_name": "MY EYES",
                    "track_id": "4kjI1gwQZRKNDkw1nI475M",
                    "album_id": "18NOKLkZETa4sWwLMIm0UZ"
                },
                {
                    "track_name": "Open Arms (feat. Travis Scott)",
                    "track_id": "6koKhrBBcExADvWuOgceNZ",
                    "album_id": "1nrVofqDRs7cpWXJ49qTnP"
                },
                {
                    "track_name": "Trance (with Travis Scott & Young Thug)",
                    "track_id": "5wG3HvLhF6Y5KTGlK0IW3J",
                    "album_id": "7txGsnDSqVMoRl6RQ9XyZP"
                },
                {
                    "track_name": "HIGHEST IN THE ROOM",
                    "track_id": "3eekarcy7kvN4yt5ZFzltW",
                    "album_id": "2uDTi1PlpSpvAv7IRAoAEU"
                }
            ]
        },
        {
            "artist_id": "2uYWxilOVlUdk4oV9DvwqK",
            "artist_name": "Mitski",
            "image_url": "https://i.scdn.co/image/ab6761610000e5eb4bdb3888818637acb71c4a13",
            "top_tracks": [
                {
                    "track_name": "My Love Mine All Mine",
                    "track_id": "3vkCueOmm7xQDoJ17W1Pm3",
                    "album_id": "2Cn1d2KgbkAqbZCJ1RzdkA"
                },
                {
                    "track_name": "Washing Machine Heart",
                    "track_id": "3jjsRKEsF42ccXf8kWR3nu",
                    "album_id": "42cH7mrkfljkqkxA2Ip9Xq"
                },
                {
                    "track_name": "I Bet on Losing Dogs",
                    "track_id": "2Co0IjcLTSHMtodwD4gzfg",
                    "album_id": "4Coa8Eb9SzjrkwWEom963Q"
                },
                {
                    "track_name": "First Love/Late Spring",
                    "track_id": "3sslYZcFKtUvIEWN9lADgr",
                    "album_id": "3I2KkX13lHXuYqfBjSOopo"
                },
                {
                    "track_name": "Francis Forever",
                    "track_id": "5411TEB6tlzvuF5A4oyldr",
                    "album_id": "3I2KkX13lHXuYqfBjSOopo"
                },
                {
                    "track_name": "Nobody",
                    "track_id": "2P5yIMu2DNeMXTyOANKS6k",
                    "album_id": "42cH7mrkfljkqkxA2Ip9Xq"
                },
                {
                    "track_name": "Liquid Smooth",
                    "track_id": "3XCveEutwTaDiekRkkfdp9",
                    "album_id": "22MICAVuz34zzqm4Se5Lga"
                },
                {
                    "track_name": "Me and My Husband",
                    "track_id": "3pANfZVFdtuVnJsE6xa5Ox",
                    "album_id": "42cH7mrkfljkqkxA2Ip9Xq"
                },
                {
                    "track_name": "I Want You",
                    "track_id": "7FHj19QQigvMH1onMYRNLn",
                    "album_id": "7K4SuWzgUEweJScduBcC6f"
                },
                {
                    "track_name": "A Pearl",
                    "track_id": "7fd3aMiuwHWKsTdZafjOfZ",
                    "album_id": "42cH7mrkfljkqkxA2Ip9Xq"
                }
            ]
        },
        {
            "artist_id": "1McMsnEElThX1knmY4oliG",
            "artist_name": "Olivia Rodrigo",
            "image_url": "https://i.scdn.co/image/ab6761610000e5ebe03a98785f3658f0b6461ec4",
            "top_tracks": [
                {
                    "track_name": "vampire",
                    "track_id": "1kuGVB7EU95pJObxwvfwKS",
                    "album_id": "1xJHno7SmdVtZAtXbdbDZp"
                },
                {
                    "track_name": "obsessed",
                    "track_id": "6tNgRQ0K2NYZ0Rb9l9DzL8",
                    "album_id": "1D06fz3cuob62ysTS8k6gu"
                },
                {
                    "track_name": "traitor",
                    "track_id": "5CZ40GBx1sQ9agT82CLQCT",
                    "album_id": "6s84u2TUpR3wdUv4NgKA2j"
                },
                {
                    "track_name": "deja vu",
                    "track_id": "6HU7h9RYOaPRFeh0R3UeAr",
                    "album_id": "6s84u2TUpR3wdUv4NgKA2j"
                },
                {
                    "track_name": "drivers license",
                    "track_id": "5wANPM4fQCJwkGd4rN57mH",
                    "album_id": "6s84u2TUpR3wdUv4NgKA2j"
                },
                {
                    "track_name": "good 4 u",
                    "track_id": "4ZtFanR9U6ndgddUvNcjcG",
                    "album_id": "6s84u2TUpR3wdUv4NgKA2j"
                },
                {
                    "track_name": "favorite crime",
                    "track_id": "5JCoSi02qi3jJeHdZXMmR8",
                    "album_id": "6s84u2TUpR3wdUv4NgKA2j"
                },
                {
                    "track_name": "happier",
                    "track_id": "2tGvwE8GcFKwNdAXMnlbfl",
                    "album_id": "6s84u2TUpR3wdUv4NgKA2j"
                },
                {
                    "track_name": "bad idea right?",
                    "track_id": "3IX0yuEVvDbnqUwMBB3ouC",
                    "album_id": "1xJHno7SmdVtZAtXbdbDZp"
                },
                {
                    "track_name": "so american",
                    "track_id": "5Jh1i0no3vJ9u4deXkb4aV",
                    "album_id": "1D06fz3cuob62ysTS8k6gu"
                }
            ]
        },
        {
            "artist_id": "73sIBHcqh3Z3NyqHKZ7FOL",
            "artist_name": "Childish Gambino",
            "image_url": "https://i.scdn.co/image/ab6761610000e5eb3ef779aa0d271adb2b6a3ded",
            "top_tracks": [
                {
                    "track_name": "Les",
                    "track_id": "0YsGMHid6sFq5PcToe3JZE",
                    "album_id": "2nkHPk6e7TgemWh07yFHxh"
                },
                {
                    "track_name": "Redbone",
                    "track_id": "0WtDGnWL2KrMCk0mI1Gpwz",
                    "album_id": "7caGY3YPOchIO8xLvTKWN4"
                },
                {
                    "track_name": "Heartbeat",
                    "track_id": "0zo4aX57COch7Wh3NRImTM",
                    "album_id": "2nkHPk6e7TgemWh07yFHxh"
                },
                {
                    "track_name": "Me and Your Mama",
                    "track_id": "4AFsRbaLKRWo3dDtjDFA2V",
                    "album_id": "7caGY3YPOchIO8xLvTKWN4"
                },
                {
                    "track_name": "3005",
                    "track_id": "5cc9Zbfp9u10sfJeKZ3h16",
                    "album_id": "62yjWIhnATHxPqGbgC9Lqr"
                },
                {
                    "track_name": "Atavista",
                    "track_id": "6Lj4RhwPsVfMn7tsA5i8jW",
                    "album_id": "692R05mxz7V6eOFoj5PMlQ"
                },
                {
                    "track_name": "Little Foot Big Foot (feat. Young Nudy)",
                    "track_id": "1SdqlTmK9P97PntBQrtf85",
                    "album_id": "692R05mxz7V6eOFoj5PMlQ"
                },
                {
                    "track_name": "III. Urn",
                    "track_id": "1wYIv0ySOwjMFWLOtrgtbo",
                    "album_id": "62yjWIhnATHxPqGbgC9Lqr"
                },
                {
                    "track_name": "Psilocybae (Millennial Love) (feat. 21 Savage, Ink & Kadhja Bonet)",
                    "track_id": "6ajiOUVtxRjYcf1EvBDoV4",
                    "album_id": "692R05mxz7V6eOFoj5PMlQ"
                },
                {
                    "track_name": "Bonfire",
                    "track_id": "25ypHCQpDX2nrDFly7eZLZ",
                    "album_id": "2nkHPk6e7TgemWh07yFHxh"
                }
            ]
        },
        {
            "artist_id": "6qqNVTkY8uBg9cP3Jd7DAH",
            "artist_name": "Billie Eilish",
            "image_url": "https://i.scdn.co/image/ab6761610000e5eb4a21b4760d2ecb7b0dcdc8da",
            "top_tracks": [
                {
                    "track_name": "LUNCH",
                    "track_id": "629DixmZGHc7ILtEntuiWE",
                    "album_id": "7aJuG4TFXa2hmE4z1yxc3n"
                },
                {
                    "track_name": "CHIHIRO",
                    "track_id": "7BRD7x5pt8Lqa1eGYC4dzj",
                    "album_id": "7aJuG4TFXa2hmE4z1yxc3n"
                },
                {
                    "track_name": "BIRDS OF A FEATHER",
                    "track_id": "6dOtVTDdiauQNBQEDOtlAB",
                    "album_id": "7aJuG4TFXa2hmE4z1yxc3n"
                },
                {
                    "track_name": "WILDFLOWER",
                    "track_id": "3QaPy1KgI7nu9FJEQUgn6h",
                    "album_id": "7aJuG4TFXa2hmE4z1yxc3n"
                },
                {
                    "track_name": "BLUE",
                    "track_id": "2prqm9sPLj10B4Wg0wE5x9",
                    "album_id": "7aJuG4TFXa2hmE4z1yxc3n"
                },
                {
                    "track_name": "SKINNY",
                    "track_id": "1CsMKhwEmNnmvHUuO5nryA",
                    "album_id": "7aJuG4TFXa2hmE4z1yxc3n"
                },
                {
                    "track_name": "L’AMOUR DE MA VIE",
                    "track_id": "6fPan2saHdFaIHuTSatORv",
                    "album_id": "7aJuG4TFXa2hmE4z1yxc3n"
                },
                {
                    "track_name": "THE GREATEST",
                    "track_id": "6TGd66r0nlPaYm3KIoI7ET",
                    "album_id": "7aJuG4TFXa2hmE4z1yxc3n"
                },
                {
                    "track_name": "What Was I Made For? [From The Motion Picture \"Barbie\"]",
                    "track_id": "6wf7Yu7cxBSPrRlWeSeK0Q",
                    "album_id": "3AafSrFIbJPH6BJHiJm1Cd"
                },
                {
                    "track_name": "THE DINER",
                    "track_id": "1LLUoftvmTjVNBHZoQyveF",
                    "album_id": "7aJuG4TFXa2hmE4z1yxc3n"
                }
            ]
        },
        {
            "artist_id": "6qqNVTkY8uBg9cP3Jd7DAH",
            "artist_name": "Billie Eilish",
            "image_url": "https://i.scdn.co/image/ab6761610000e5eb4a21b4760d2ecb7b0dcdc8da",
            "top_tracks": [
                {
                    "track_name": "LUNCH",
                    "track_id": "629DixmZGHc7ILtEntuiWE",
                    "album_id": "7aJuG4TFXa2hmE4z1yxc3n"
                },
                {
                    "track_name": "CHIHIRO",
                    "track_id": "7BRD7x5pt8Lqa1eGYC4dzj",
                    "album_id": "7aJuG4TFXa2hmE4z1yxc3n"
                },
                {
                    "track_name": "BIRDS OF A FEATHER",
                    "track_id": "6dOtVTDdiauQNBQEDOtlAB",
                    "album_id": "7aJuG4TFXa2hmE4z1yxc3n"
                },
                {
                    "track_name": "WILDFLOWER",
                    "track_id": "3QaPy1KgI7nu9FJEQUgn6h",
                    "album_id": "7aJuG4TFXa2hmE4z1yxc3n"
                },
                {
                    "track_name": "BLUE",
                    "track_id": "2prqm9sPLj10B4Wg0wE5x9",
                    "album_id": "7aJuG4TFXa2hmE4z1yxc3n"
                },
                {
                    "track_name": "SKINNY",
                    "track_id": "1CsMKhwEmNnmvHUuO5nryA",
                    "album_id": "7aJuG4TFXa2hmE4z1yxc3n"
                },
                {
                    "track_name": "L’AMOUR DE MA VIE",
                    "track_id": "6fPan2saHdFaIHuTSatORv",
                    "album_id": "7aJuG4TFXa2hmE4z1yxc3n"
                },
                {
                    "track_name": "THE GREATEST",
                    "track_id": "6TGd66r0nlPaYm3KIoI7ET",
                    "album_id": "7aJuG4TFXa2hmE4z1yxc3n"
                },
                {
                    "track_name": "What Was I Made For? [From The Motion Picture \"Barbie\"]",
                    "track_id": "6wf7Yu7cxBSPrRlWeSeK0Q",
                    "album_id": "3AafSrFIbJPH6BJHiJm1Cd"
                },
                {
                    "track_name": "THE DINER",
                    "track_id": "1LLUoftvmTjVNBHZoQyveF",
                    "album_id": "7aJuG4TFXa2hmE4z1yxc3n"
                }
            ]
        },
        {
            "artist_id": "1HY2Jd0NmPuamShAr6KMms",
            "artist_name": "Lady Gaga",
            "image_url": "https://i.scdn.co/image/ab6761610000e5ebc8d3d98a1bccbe71393dbfbf",
            "top_tracks": [
                {
                    "track_name": "Poker Face",
                    "track_id": "1QV6tiMFM6fSOKOGLMHYYg",
                    "album_id": "1qwlxZTNLe1jq3b0iidlue"
                },
                {
                    "track_name": "Shallow",
                    "track_id": "2VxeLyX666F8uXCJ0dZF8B",
                    "album_id": "4sLtOBOzn4s3GDUv3c5oJD"
                },
                {
                    "track_name": "Bad Romance",
                    "track_id": "0SiywuOBRcynK0uKGWdCnn",
                    "album_id": "6rePArBMb5nLWEaY9aQqL4"
                },
                {
                    "track_name": "Just Dance",
                    "track_id": "1dzQoRqT5ucxXVaAhTcT0J",
                    "album_id": "1qwlxZTNLe1jq3b0iidlue"
                },
                {
                    "track_name": "Always Remember Us This Way",
                    "track_id": "2rbDhOo9Fh61Bbu23T2qCk",
                    "album_id": "3edjzMAVB9RYRd4UcZBchx"
                },
                {
                    "track_name": "Judas",
                    "track_id": "7F25roCtYi55JouckaayPC",
                    "album_id": "6LY3AerY6KNGOPsNPL63Kk"
                },
                {
                    "track_name": "Paparazzi",
                    "track_id": "02XnQdf7sipaKBBHixz3Zp",
                    "album_id": "1qwlxZTNLe1jq3b0iidlue"
                },
                {
                    "track_name": "Telephone",
                    "track_id": "7rl7ao5pb9BhvAzPdWStxi",
                    "album_id": "6DGZdMi124iOOih9GMlhN2"
                },
                {
                    "track_name": "Bloody Mary",
                    "track_id": "53jnnqFSRGMDB9ADrNriCA",
                    "album_id": "6LY3AerY6KNGOPsNPL63Kk"
                },
                {
                    "track_name": "Applause",
                    "track_id": "5ka2ajep9OAvU5Sgduhiex",
                    "album_id": "2eRJUtI7nXrQ5uYQ7tzTo9"
                }
            ]
        },
        {
            "artist_id": "5INjqkS1o8h1imAzPqGZBb",
            "artist_name": "Tame Impala",
            "image_url": "https://i.scdn.co/image/ab6761610000e5eb90357ef28b3a012a1d1b2fa2",
            "top_tracks": [
                {
                    "track_name": "The Less I Know The Better",
                    "track_id": "6K4t31amVTZDgR3sKmwUJJ",
                    "album_id": "79dL7FLiJFOO0EoehUHQBv"
                },
                {
                    "track_name": "Borderline",
                    "track_id": "5hM5arv9KDbCHS0k9uqwjr",
                    "album_id": "31qVWUdRrlb8thMvts0yYL"
                },
                {
                    "track_name": "Let It Happen",
                    "track_id": "2X485T9Z5Ly0xyaghN73ed",
                    "album_id": "79dL7FLiJFOO0EoehUHQBv"
                },
                {
                    "track_name": "New Person, Same Old Mistakes",
                    "track_id": "52ojopYMUzeNcudsoz7O9D",
                    "album_id": "79dL7FLiJFOO0EoehUHQBv"
                },
                {
                    "track_name": "Neverender",
                    "track_id": "3aQ9MHkMeL7Yu7jpyF62xn",
                    "album_id": "6ooBxhsOVedpX4zPTCyL86"
                },
                {
                    "track_name": "Eventually",
                    "track_id": "5M4yti0QxgqJieUYaEXcpw",
                    "album_id": "79dL7FLiJFOO0EoehUHQBv"
                },
                {
                    "track_name": "Feels Like We Only Go Backwards",
                    "track_id": "0LtOwyZoSNZKJWHqjzADpW",
                    "album_id": "3C2MFZ2iHotUQOSBzdSvM7"
                },
                {
                    "track_name": "Elephant",
                    "track_id": "6qZjm61s6u8Ead9sWxCDro",
                    "album_id": "3C2MFZ2iHotUQOSBzdSvM7"
                },
                {
                    "track_name": "One More Hour",
                    "track_id": "0mO6oS60RST2sWmN2FKknP",
                    "album_id": "31qVWUdRrlb8thMvts0yYL"
                },
                {
                    "track_name": "One Night/All Night",
                    "track_id": "2Oidi4pAbR9X81PBaV71N8",
                    "album_id": "6ooBxhsOVedpX4zPTCyL86"
                }
            ]
        },
        {
            "artist_id": "7tYKF4w9nC0nq9CsPZTHyP",
            "artist_name": "SZA",
            "image_url": "https://i.scdn.co/image/ab6761610000e5eb0895066d172e1f51f520bc65",
            "top_tracks": [
                {
                    "track_name": "Saturn",
                    "track_id": "1bjeWoagtHmUKputLVyDxQ",
                    "album_id": "1fmBMCSSkSlvxyoy1vut2k"
                },
                {
                    "track_name": "Snooze",
                    "track_id": "4iZ4pt7kvcaH6Yo8UoZ4s2",
                    "album_id": "07w0rG5TETcyihsEIZR3qG"
                },
                {
                    "track_name": "Kill Bill",
                    "track_id": "1Qrg8KqiBpW07V7PNxwwwL",
                    "album_id": "1nrVofqDRs7cpWXJ49qTnP"
                },
                {
                    "track_name": "All The Stars (with SZA)",
                    "track_id": "3GCdLUSnKSMJhs4Tj6CV3s",
                    "album_id": "3pLdWdkj83EYfDN6H2N8MR"
                },
                {
                    "track_name": "Nobody Gets Me",
                    "track_id": "5Y35SjAfXjjG0sFQ3KOxmm",
                    "album_id": "07w0rG5TETcyihsEIZR3qG"
                },
                {
                    "track_name": "Good Days",
                    "track_id": "4PMqSO5qyjpvzhlLI5GnID",
                    "album_id": "07w0rG5TETcyihsEIZR3qG"
                },
                {
                    "track_name": "Rich Baby Daddy (feat. Sexyy Red & SZA)",
                    "track_id": "1yeB8MUNeLo9Ek1UEpsyz6",
                    "album_id": "4czdORdCWP9umpbhFXK2fW"
                },
                {
                    "track_name": "Open Arms (feat. Travis Scott)",
                    "track_id": "6koKhrBBcExADvWuOgceNZ",
                    "album_id": "1nrVofqDRs7cpWXJ49qTnP"
                },
                {
                    "track_name": "Kiss Me More (feat. SZA)",
                    "track_id": "3DarAbFujv6eYNliUTyqtz",
                    "album_id": "1nAQbHeOWTfQzbOoFrvndW"
                },
                {
                    "track_name": "Broken Clocks",
                    "track_id": "2fXwCWkh6YG5zU1IyvQrbs",
                    "album_id": "76290XdXVF9rPzGdNRWdCh"
                }
            ]
        },
        {
            "artist_id": "57vWImR43h4CaDao012Ofp",
            "artist_name": "Steve Lacy",
            "image_url": "https://i.scdn.co/image/ab6761610000e5eb09ac9d040c168d4e4f58eb42",
            "top_tracks": [
                {
                    "track_name": "Dark Red",
                    "track_id": "3EaJDYHA0KnX88JvDhL9oa",
                    "album_id": "7vrsFZNVhrriKh0SZKJW41"
                },
                {
                    "track_name": "Bad Habit",
                    "track_id": "4k6Uh1HXdhtusDW5y8Gbvy",
                    "album_id": "3Ks0eeH0GWpY4AU20D5HPD"
                },
                {
                    "track_name": "Some",
                    "track_id": "4riDfclV7kPDT9D58FpmHd",
                    "album_id": "4POiurFeB5bDsF9yBwOxbh"
                },
                {
                    "track_name": "C U Girl",
                    "track_id": "6FBzhcfgGacfXF3AmtfEaX",
                    "album_id": "33jE0rzk63VdTJcDukmjRa"
                },
                {
                    "track_name": "Infrunami",
                    "track_id": "0f8eRy9A0n6zXpKSHSCAEp",
                    "album_id": "6m5qlaMzLtNsQDj3DQY5ji"
                },
                {
                    "track_name": "Static",
                    "track_id": "4OmfWzukSVD140NiAIEjem",
                    "album_id": "3Ks0eeH0GWpY4AU20D5HPD"
                },
                {
                    "track_name": "Uuuu",
                    "track_id": "6M0EP76qW9TG4SNU0agu94",
                    "album_id": "6m5qlaMzLtNsQDj3DQY5ji"
                },
                {
                    "track_name": "N Side",
                    "track_id": "12ILYlOEfWL8ei0BEgFJn0",
                    "album_id": "4hvsfS6cytmO16IfAptVA9"
                },
                {
                    "track_name": "Ryd",
                    "track_id": "5Ha9IheRrkDyr7ZdhaRsWb",
                    "album_id": "2J3aZLAPphJi80QXibyrNr"
                },
                {
                    "track_name": "Bad Habit - Sped Up",
                    "track_id": "4i7HqWsN7iJzsXpsW5h1nb",
                    "album_id": "5vg6tTa6EHy0c9NNSOSM8T"
                }
            ]
        },
        {
            "artist_id": "77SW9BnxLY8rJ0RciFqkHh",
            "artist_name": "The Neighbourhood",
            "image_url": "https://i.scdn.co/image/ab6761610000e5ebdf0b5ac84376a0a4b2166816",
            "top_tracks": [
                {
                    "track_name": "Sweater Weather",
                    "track_id": "2QjOHCTQ1Jl3zawyYOpxh6",
                    "album_id": "4xkM0BwLM9H2IUcbYzpcBI"
                },
                {
                    "track_name": "Daddy Issues",
                    "track_id": "5E30LdtzQTGqRvNd7l6kG5",
                    "album_id": "18iFxjZugvKhuNNMbLjZJF"
                },
                {
                    "track_name": "Softcore",
                    "track_id": "2K7xn816oNHJZ0aVqdQsha",
                    "album_id": "0ODLCdHBFVvKwJGeSfd1jy"
                },
                {
                    "track_name": "You Get Me So High",
                    "track_id": "7zwn1eykZtZ5LODrf7c0tS",
                    "album_id": "0ODLCdHBFVvKwJGeSfd1jy"
                },
                {
                    "track_name": "Reflections",
                    "track_id": "2xql0pid3EUwW38AsywxhV",
                    "album_id": "0ODLCdHBFVvKwJGeSfd1jy"
                },
                {
                    "track_name": "Pretty Boy",
                    "track_id": "7IL8PSVwLOJxqYne6azxQv",
                    "album_id": "4uNgt1uQs6wZRm4giB3shX"
                },
                {
                    "track_name": "Afraid",
                    "track_id": "7brQHA2CgQpcMBiOlfiXYb",
                    "album_id": "4xkM0BwLM9H2IUcbYzpcBI"
                },
                {
                    "track_name": "Cry Baby",
                    "track_id": "0EfsDEYaSjGYd66Pr881nq",
                    "album_id": "18iFxjZugvKhuNNMbLjZJF"
                },
                {
                    "track_name": "The Beach",
                    "track_id": "2u0CelO5c81XS7z3dGpHbS",
                    "album_id": "18iFxjZugvKhuNNMbLjZJF"
                },
                {
                    "track_name": "Nervous",
                    "track_id": "113xf7t4qNM7038YJvauik",
                    "album_id": "0ODLCdHBFVvKwJGeSfd1jy"
                }
            ]
        },
        {
            "artist_id": "2FXC3k01G6Gw61bmprjgqS",
            "artist_name": "Hozier",
            "image_url": "https://i.scdn.co/image/ab6761610000e5ebad85a585103dfc2f3439119a",
            "top_tracks": [
                {
                    "track_name": "Too Sweet",
                    "track_id": "5Z0UnEtpLDQyYlWwgi8m9C",
                    "album_id": "3P4SQqMMgjqfqVxgLwtYRk"
                },
                {
                    "track_name": "Take Me To Church",
                    "track_id": "3dYD57lRAUcMHufyqn9GcI",
                    "album_id": "0Uv83rRhY5QvHKkQoULRKk"
                },
                {
                    "track_name": "Northern Attitude (with Hozier)",
                    "track_id": "6pBeLF2GZS3NNwV4DBvtg5",
                    "album_id": "3qBWNcWifNhUKJAWzswdJY"
                },
                {
                    "track_name": "Work Song",
                    "track_id": "35PKfoynRpVFoAUE3D5Kc6",
                    "album_id": "0Uv83rRhY5QvHKkQoULRKk"
                },
                {
                    "track_name": "Almost (Sweet Music)",
                    "track_id": "7uttm8Iurm5uK67Vr9G2Sp",
                    "album_id": "5j1ZsFyNCsnt62prbs85eE"
                },
                {
                    "track_name": "Someone New",
                    "track_id": "22sS7JkzeVeq4vOPCB6Fbj",
                    "album_id": "0Uv83rRhY5QvHKkQoULRKk"
                },
                {
                    "track_name": "Would That I",
                    "track_id": "0L3oQdYUvVbsOOPJSkZ3C3",
                    "album_id": "5j1ZsFyNCsnt62prbs85eE"
                },
                {
                    "track_name": "Eat Your Young",
                    "track_id": "3hbKcj640iYmPQgecainOr",
                    "album_id": "0TFpENEamBfIfGISdSTXFB"
                },
                {
                    "track_name": "Like Real People Do",
                    "track_id": "4LGJ2pLDvTRnul3EcZoYkX",
                    "album_id": "0Uv83rRhY5QvHKkQoULRKk"
                },
                {
                    "track_name": "Jackie And Wilson",
                    "track_id": "5xo1Gj4WTssjQgQ0w03cf2",
                    "album_id": "0Uv83rRhY5QvHKkQoULRKk"
                }
            ]
        },
        {
            "artist_id": "4gzpq5DPGxSnKTe4SA8HAU",
            "artist_name": "Coldplay",
            "image_url": "https://i.scdn.co/image/ab6761610000e5ebc878d7a8f8299a3a09e29fb6",
            "top_tracks": [
                {
                    "track_name": "Yellow",
                    "track_id": "3AJwUDP919kvQ9QcozQPxg",
                    "album_id": "6ZG5lRT77aJ3btmArcykra"
                },
                {
                    "track_name": "Something Just Like This",
                    "track_id": "6RUKPb4LETWmmr3iAEQktW",
                    "album_id": "4JPguzRps3kuWDD5GS6oXr"
                },
                {
                    "track_name": "Viva La Vida",
                    "track_id": "1mea3bSkSGXuIRvnydlB5b",
                    "album_id": "1CEODgTmTwLyabvwd7HBty"
                },
                {
                    "track_name": "A Sky Full of Stars",
                    "track_id": "0FDzzruyVECATHXKHFs9eJ",
                    "album_id": "2G4AUqfwxcV1UdQjm2ouYr"
                },
                {
                    "track_name": "The Scientist",
                    "track_id": "75JFxkI2RXiU7L9VXzMkle",
                    "album_id": "0RHX9XECH8IVI3LNgWDpmQ"
                },
                {
                    "track_name": "Sparks",
                    "track_id": "7D0RhFcb3CrfPuTJ0obrod",
                    "album_id": "6ZG5lRT77aJ3btmArcykra"
                },
                {
                    "track_name": "Hymn for the Weekend",
                    "track_id": "3RiPr603aXAoi4GHyXx0uy",
                    "album_id": "3cfAM8b8KqJRoIzt3zLKqw"
                },
                {
                    "track_name": "Clocks",
                    "track_id": "0BCPKOYdS2jbQ8iyB56Zns",
                    "album_id": "0RHX9XECH8IVI3LNgWDpmQ"
                },
                {
                    "track_name": "Paradise",
                    "track_id": "6nek1Nin9q48AVZcWs9e9D",
                    "album_id": "2R7iJz5uaHjLEVnMkloO18"
                },
                {
                    "track_name": "Fix You",
                    "track_id": "7LVHVU3tWfcxj5aiPFEW4Q",
                    "album_id": "4E7bV0pzG0LciBSWTszra6"
                }
            ]
        },
        {
            "artist_id": "6M2wZ9GZgrQXHCFfjv46we",
            "artist_name": "Dua Lipa",
            "image_url": "https://i.scdn.co/image/ab6761610000e5eb0c68f6c95232e716f0abee8d",
            "top_tracks": [
                {
                    "track_name": "Training Season",
                    "track_id": "5b5cPscqVEMChvDqscVw26",
                    "album_id": "1Mo92916G2mmG7ajpmSVrc"
                },
                {
                    "track_name": "Houdini",
                    "track_id": "6D8y7Bck8h11byRY88Pt2z",
                    "album_id": "1Mo92916G2mmG7ajpmSVrc"
                },
                {
                    "track_name": "Illusion",
                    "track_id": "5q0EXnBYyeCdXD72FzJxH0",
                    "album_id": "1Mo92916G2mmG7ajpmSVrc"
                },
                {
                    "track_name": "Cold Heart - PNAU Remix",
                    "track_id": "6JIC3hbC28JZKZ8AlAqX8h",
                    "album_id": "2Gd77sRs3Y8z8V08Hj6EzC"
                },
                {
                    "track_name": "Dance The Night - From Barbie The Album",
                    "track_id": "1vYXt7VSjH9JIM5oRRo7vA",
                    "album_id": "5cH7FqB7JD5q1tJXJ7FHYu"
                },
                {
                    "track_name": "Don't Start Now",
                    "track_id": "3PfIrDoz19wz7qK7tYeu62",
                    "album_id": "7fJJK56U9fHixgO0HQkhtI"
                },
                {
                    "track_name": "One Kiss (with Dua Lipa)",
                    "track_id": "7ef4DlsgrMEH11cDZd32M6",
                    "album_id": "7GEzhoTiqcPYkOprWQu581"
                },
                {
                    "track_name": "Levitating (feat. DaBaby)",
                    "track_id": "5nujrmhLynf4yMoMtj8AQF",
                    "album_id": "5lKlFlReHOLShQKyRv6AL9"
                },
                {
                    "track_name": "These Walls",
                    "track_id": "7b6sWLSnbZhSIeqNGrJ4py",
                    "album_id": "1Mo92916G2mmG7ajpmSVrc"
                },
                {
                    "track_name": "New Rules",
                    "track_id": "2ekn2ttSfGqwhhate0LSR0",
                    "album_id": "01sfgrNbnnPUEyz6GZYlt9"
                }
            ]
        }
    ]
}